LICENSE
MANIFEST.in
README.rst
pytest.ini
requirements-dev.pip
requirements.pip
setup.py
overalls/__init__.py
overalls/__init__.pyc
overalls/__pycache__
overalls/cmd.py
overalls/cmd.pyc
overalls/collectors
overalls/core.py
overalls/core.pyc
overalls/tests
overalls/uploaders
overalls.egg-info/PKG-INFO
overalls.egg-info/SOURCES.txt
overalls.egg-info/dependency_links.txt
overalls.egg-info/requires.txt
overalls.egg-info/top_level.txt
overalls/collectors/__init__.py
overalls/collectors/lcov.py
overalls/collectors/python.py
overalls/collectors/tests/__init__.py
overalls/collectors/tests/example.lcov
overalls/collectors/tests/test_lcov.py
overalls/tests/__init__.py
overalls/tests/test_cmd.py
overalls/tests/test_core.py
overalls/tests/utils.py
overalls/uploaders/__init__.py
overalls/uploaders/coveralls.py
overalls/uploaders/tests/__init__.py
scripts/overalls