Metadata-Version: 1.1
Name: overalls
Version: 0.1.1
Summary: Coveralls coverage uploader.
Home-page: https://github.com/hodgestar/overalls
Author: Simon Cross
Author-email: hodgestar@gmail.com
License: UNKNOWN
Platform: UNKNOWN
Classifier: Development Status :: 4 - Beta
Classifier: Intended Audience :: Developers
Classifier: License :: OSI Approved :: BSD License
Classifier: Operating System :: POSIX
Classifier: Programming Language :: Python
